{
    "title": "Bratrství ve sněmovně",
    "url": "https://echo24.cz/a/HdsKX/komentar-ondrej-stindl-bratrstvi-ve-snemovne",
    "date": "2025-11-07T00:01:00+01:00",
    "author": "Ondřej Štindl",
    "source": "echo24.cz",
    "content_snippet": "KOMENTÁŘ\n\nPoslanecká sněmovna Tomio Okamura Hayato Okamura\n\nAdam Růžička\n\nRoku 1997 byla v Izraeli u moci první vláda premiéra Benjamina Netanjahua a tzv. mírový proces pomalu, ale jistě směřoval do s…",
    "full_content": "KOMENTÁŘ\n\nPoslanecká sněmovna Tomio Okamura Hayato Okamura\n\nAdam Růžička\n\nRoku 1997 byla v Izraeli u moci první vláda premiéra Benjamina Netanjahua a tzv. mírový proces pomalu, ale jistě směřoval do stavu klinické smrti. Toho roku začal do časopisu Roš chodeš, což je měsíčník Federace židovských obcí, psát první komentáře novinář Zbyněk Petráček, jenž je tam měsíc co měsíc tiskne dosud, což znamená téměř nepřetržitých třicet let. Je to u nás pravděpodobně nejsouvislejší a také nejkompaktnější řada referování o dění ve Svaté zemi, o její situaci vnitřní i vnější, o konfliktech, kterými prochází a kterým musí čelit, o vývoji a průběhu těchto konfliktů a souvislostech s nimi spojených. Výbor z těchto komentářů vychází nyní v obsáhlé knize (580 stran) nazvané prostě Izrael: 1997–2025.\n\nJiří Peňás\n\nMartin Weiss\n\nMaciej Ruczaj\n\nBABIŠ A AGROFERT\n\nvra , 7. listopadu 2025 11:20\n\nPODPORA UKRAJINY\n\njkr\n\nStrhnout ukrajinskou vlajku z budovy parlamentu evropské země, jejíž bratrský národ podporuje Ukrajince v tomto spravedlivém boji, je pochybný čin. Na síti X ...\n\nAdam Růžička\n\nJiří Peňás\n\nMartin Weiss\n\nMaciej Ruczaj\n\nDaniel Kaiser\n\n11:20\n\n11:03\n\n10:47\n\n10:32\n\n09:31\n\n08:54\n\n08:21\n\n08:20\n\n07:36\n\n06:49\n\njkr , 7. listopadu 2025 11:51\n\nPODPORA UKRAJINY\n\nEcho24 , 5. listopadu 2025\n\nPŘEDSEDA SNĚMOVNY\n\njkr , 5. listopadu 2025\n\nNOVÁ SNĚMOVNA",
    "tags": [
        "Poslanecká sněmovna",
        "Tomio Okamura",
        "Hayato Okamura",
        "Politika"
    ]
}